django_spectra-1.0.2.dist-info/licenses/LICENSE
spectra/__init__.py
spectra/admin.py
spectra/apps.py
spectra/config.py
spectra/context_processors.py
spectra/middleware.py
spectra/models.py
spectra/plugins.py
spectra/urls.py
spectra/views.py
spectra/migrations/0001_initial.py
spectra/migrations/__init__.py
spectra/static/spectra/css/app.min.css
spectra/static/spectra/css/icons.min.css
spectra/static/spectra/css/layout.css
spectra/static/spectra/css/spectra.css
spectra/static/spectra/css/themes/dark.css
spectra/static/spectra/css/themes/light.css
spectra/static/spectra/fonts/boxicons.eot
spectra/static/spectra/fonts/boxicons.svg
spectra/static/spectra/fonts/boxicons.ttf
spectra/static/spectra/fonts/boxicons.woff
spectra/static/spectra/fonts/boxicons.woff2
spectra/static/spectra/fonts/remixicon.eot
spectra/static/spectra/fonts/remixicon.svg
spectra/static/spectra/fonts/remixicon.symbol.svg
spectra/static/spectra/fonts/remixicon.ttf
spectra/static/spectra/fonts/remixicon.woff
spectra/static/spectra/fonts/remixicon.woff2
spectra/static/spectra/images/404.svg
spectra/static/spectra/images/agent-1.png
spectra/static/spectra/images/analytics-m.png
spectra/static/spectra/images/bg-pattern.svg
spectra/static/spectra/images/chip.png
spectra/static/spectra/images/contactless-payment.png
spectra/static/spectra/images/customer-bg.jpg
spectra/static/spectra/images/dhl.png
spectra/static/spectra/images/e-shoes.png
spectra/static/spectra/images/favicon.ico
spectra/static/spectra/images/fedex.png
spectra/static/spectra/images/happy-man.png
spectra/static/spectra/images/home-2.png
spectra/static/spectra/images/logo-dark copy.png
spectra/static/spectra/images/logo-light.png
spectra/static/spectra/images/logo-sm.png
spectra/static/spectra/images/maintenance.svg
spectra/static/spectra/images/money.png
spectra/static/spectra/images/party.png
spectra/static/spectra/images/trophy.png
spectra/static/spectra/images/ups.png
spectra/static/spectra/images/app-calendar/facebook.png
django_spectra-1.0.2.dist-info/METADATA
django_spectra-1.0.2.dist-info/WHEEL
django_spectra-1.0.2.dist-info/top_level.txt
django_spectra-1.0.2.dist-info/RECORD
