Metadata-Version: 2.4
Name: django-spectra
Version: 1.0.2
Summary: A modern, beautiful, and highly customizable Django admin theme
Home-page: https://github.com/sundaradh/django-spectra
Author: Sundar Adhikari
Author-email: Sundar Adhikari <abcsundaradhikari123@gmail.com>
License: MIT
Project-URL: Homepage, https://github.com/sundaradh/django-spectra
Project-URL: Documentation, https://github.com/sundaradh/django-spectra#readme
Project-URL: Repository, https://github.com/sundaradh/django-spectra
Project-URL: Issues, https://github.com/sundaradh/django-spectra/issues
Keywords: django,admin,theme,dashboard,ui,modern,customizable
Classifier: Development Status :: 4 - Beta
Classifier: Environment :: Web Environment
Classifier: Framework :: Django
Classifier: Framework :: Django :: 4.2
Classifier: Framework :: Django :: 5.0
Classifier: Framework :: Django :: 5.1
Classifier: Intended Audience :: Developers
Classifier: License :: OSI Approved :: MIT License
Classifier: Operating System :: OS Independent
Classifier: Programming Language :: Python
Classifier: Programming Language :: Python :: 3
Classifier: Programming Language :: Python :: 3.9
Classifier: Programming Language :: Python :: 3.10
Classifier: Programming Language :: Python :: 3.11
Classifier: Programming Language :: Python :: 3.12
Classifier: Topic :: Internet :: WWW/HTTP
Classifier: Topic :: Internet :: WWW/HTTP :: Dynamic Content
Classifier: Topic :: Software Development :: Libraries :: Python Modules
Requires-Python: >=3.9
License-File: LICENSE
Requires-Dist: Django>=4.2
Requires-Dist: Pillow>=9.0
Provides-Extra: dev
Requires-Dist: pytest>=7.0; extra == "dev"
Requires-Dist: pytest-django>=4.5; extra == "dev"
Requires-Dist: black>=23.0; extra == "dev"
Requires-Dist: flake8>=6.0; extra == "dev"
Requires-Dist: isort>=5.12; extra == "dev"
Dynamic: author
Dynamic: home-page
Dynamic: license-file
Dynamic: requires-python
